README.md
setup.py
fson/__init__.py
fson/fson.py
fson.egg-info/PKG-INFO
fson.egg-info/SOURCES.txt
fson.egg-info/dependency_links.txt
fson.egg-info/not-zip-safe
fson.egg-info/top_level.txt