Metadata-Version: 1.0
Name: fson
Version: 0.0.2
Summary: toolbox for fast operate json
Home-page: http://www.memect.cn
Author: wangshuang
Author-email: wangshuang@memect.co
License: MIT
Platform: UNKNOWN
